is_is_odd/__init__.py
is_is_odd/_version.py
is_is_odd-0.0.2.dist-info/licenses/LICENSE
is_is_odd-0.0.2.dist-info/METADATA
is_is_odd-0.0.2.dist-info/WHEEL
is_is_odd-0.0.2.dist-info/top_level.txt
is_is_odd-0.0.2.dist-info/RECORD
